simt_emlite/__init__.py
simt_emlite/cli/emop.cp313-win_amd64.pyd
simt_emlite/cli/mediators.cp313-win_amd64.pyd
simt_emlite/cli/profile_download.cp313-win_amd64.pyd
simt_emlite/cli/replica_check_missing.cp313-win_amd64.pyd
simt_emlite/cli/replicas_compare.cp313-win_amd64.pyd
simt_emlite/dto/three_phase_intervals.cp313-win_amd64.pyd
simt_emlite/emlite/__init__.py
simt_emlite/emlite/emlite_api.cp313-win_amd64.pyd
simt_emlite/emlite/emlite_net.cp313-win_amd64.pyd
simt_emlite/jobs/__init__.py
simt_emlite/jobs/auto_topup_job.cp313-win_amd64.pyd
simt_emlite/jobs/future_tariffs_update.cp313-win_amd64.pyd
simt_emlite/jobs/future_tariffs_update_all.cp313-win_amd64.pyd
simt_emlite/jobs/mediators_recover_failed.cp313-win_amd64.pyd
simt_emlite/jobs/meter_sync.cp313-win_amd64.pyd
simt_emlite/jobs/meter_sync_all.cp313-win_amd64.pyd
simt_emlite/jobs/prepay_enabled_flip.cp313-win_amd64.pyd
simt_emlite/jobs/profile_log_fetch.cp313-win_amd64.pyd
simt_emlite/jobs/push_topup_token.cp313-win_amd64.pyd
simt_emlite/jobs/push_topup_tokens_all.cp313-win_amd64.pyd
simt_emlite/jobs/three_phase_intervals_fetch.cp313-win_amd64.pyd
simt_emlite/jobs/update_meter_clocks.cp313-win_amd64.pyd
simt_emlite/jobs/util.cp313-win_amd64.pyd
simt_emlite/mediator/client.cp313-win_amd64.pyd
simt_emlite/mediator/mediator_client_exception.cp313-win_amd64.pyd
simt_emlite/mediator/grpc/client.cp313-win_amd64.pyd
simt_emlite/mediator/grpc/grpc_codegen.cp313-win_amd64.pyd
simt_emlite/mediator/grpc/server.cp313-win_amd64.pyd
simt_emlite/mediator/grpc/exception/EmliteConnectionFailure.cp313-win_amd64.pyd
simt_emlite/mediator/grpc/exception/EmliteEOFError.cp313-win_amd64.pyd
simt_emlite/mediator/grpc/generated/mediator_pb2.cp313-win_amd64.pyd
simt_emlite/mediator/grpc/generated/mediator_pb2_grpc.cp313-win_amd64.pyd
simt_emlite/orchestrate/__init__.py
simt_emlite/orchestrate/adapter/__init__.py
simt_emlite/orchestrate/adapter/adapter_utils.cp313-win_amd64.pyd
simt_emlite-0.28.6.dist-info/licenses/LICENSE
simt_emlite-0.28.6.dist-info/METADATA
simt_emlite-0.28.6.dist-info/WHEEL
simt_emlite-0.28.6.dist-info/entry_points.txt
simt_emlite-0.28.6.dist-info/top_level.txt
simt_emlite-0.28.6.dist-info/RECORD
