Metadata-Version: 2.4
Name: simt-emlite
Version: 0.28.6
Summary: API and CLI for communicating with the Emlite meters via EMOP
Author-email: Chris Hatch <chris@cepro.energy>
Requires-Python: <4.0,>=3.13
License-File: LICENSE
Requires-Dist: grpcio==1.73.1
Requires-Dist: tenacity==8.5.0
Requires-Dist: supabase==2.15.2
Requires-Dist: crcmod==1.7
Requires-Dist: structlog==24.4.0
Requires-Dist: docker==7.1.0
Requires-Dist: protobuf==6.31.1
Requires-Dist: python-dotenv==1.0.1
Requires-Dist: python-socks==2.5.0
Requires-Dist: rich==13.7.1
Requires-Dist: dnspython==2.6.1
Requires-Dist: httpx==0.27.0
Requires-Dist: argcomplete>=3.4.0
Requires-Dist: types-requests==2.32.4.20250611
Requires-Dist: emop-frame-protocol==0.4.14
Requires-Dist: simt-fly-machines==0.2.4
Requires-Dist: javaproperties<0.9.0,>=0.8.2
Dynamic: license-file
